carmen/__init__.py
carmen/cli.py
carmen/location.py
carmen/names.py
carmen/resolver.py
carmen/data/geonames_locations.json
carmen/data/geonames_locations[bk].json
carmen/data/geonames_locations_combined.json
carmen/data/geonames_locations_demo.json
carmen/data/geonames_locations_only.json
carmen/data/locations.json
carmen/resolvers/__init__.py
carmen/resolvers/geocode.py
carmen/resolvers/place.py
carmen/resolvers/profile.py
carmen/resolvers/timezone.py
carmen-2.0.0.dist-info/LICENSE
carmen-2.0.0.dist-info/METADATA
carmen-2.0.0.dist-info/WHEEL
carmen-2.0.0.dist-info/top_level.txt
carmen-2.0.0.dist-info/zip-safe
carmen-2.0.0.dist-info/RECORD
