Metadata-Version: 2.1
Name: carmen
Version: 2.0.0
Summary: Geolocation for Twitter
Home-page: https://github.com/mdredze/carmen-python
Author: Jack Jingyu Zhang, Alexandra DeLucia, Roger Que, and Mark Dredze
Author-email: mark@dredze.com
License: 2-clause BSD
Platform: UNKNOWN
Requires-Dist: geopy (>=1.11.0)
Requires-Dist: jsonlines (>=3.1.0)
